{
  "action_fingerprints": {
    "utter_greet": {
      "slots": []
    }, 
    "utter_ending": {
      "slots": []
    }, 
    "action_listen": {
      "slots": [
        "passcode", 
        "password", 
        "using_what", 
        "question_yes_no", 
        "email"
      ]
    }, 
    "action_card_replace": {
      "slots": [
        "passcode", 
        "requested_slot", 
        "card_perm", 
        "card_replace_with"
      ]
    }, 
    "utter_positive_reply": {
      "slots": []
    }, 
    "action_get_access": {
      "slots": [
        "access", 
        "password", 
        "email", 
        "requested_slot"
      ]
    }, 
    "action_card_service": {
      "slots": [
        "passcode", 
        "status_access", 
        "card_permission", 
        "requested_slot", 
        "card_perm"
      ]
    }, 
    "utter_ask_passcode": {
      "slots": []
    }, 
    "utter_first_access": {
      "slots": []
    }
  }, 
  "policy_names": [
    "rasa_core.policies.memoization.MemoizationPolicy", 
    "rasa_core.policies.keras_policy.KerasPolicy"
  ], 
  "ensemble_name": "rasa_core.policies.ensemble.SimplePolicyEnsemble", 
  "max_histories": [
    10, 
    5
  ], 
  "rasa_core": "0.10.4"
}